README.md
setup.py
yuhang/__init__.py
yuhang.egg-info/PKG-INFO
yuhang.egg-info/SOURCES.txt
yuhang.egg-info/dependency_links.txt
yuhang.egg-info/entry_points.txt
yuhang.egg-info/top_level.txt
yuhang/cli/__init__.py
yuhang/cli/calc.py